seraa/__init__.py
seraa/axioms/__init__.py
seraa/axioms/choice.py
seraa/axioms/constraint.py
seraa/axioms/entanglement.py
seraa/axioms/foundation.py
seraa/axioms/htlp.py
seraa/axioms/measurement.py
seraa/axioms/resonance.py
seraa/axioms/superposition.py
seraa/axioms/uncertainty.py
seraa/cli/__init__.py
seraa/cli/chat.py
seraa/cli/constraint_explanations.py
seraa/cli/evaluate.py
seraa/core/__init__.py
seraa/core/agent.py
seraa/core/monitor.py
seraa/core/ternary.py
seraa/dsl/__init__.py
seraa/llm/__init__.py
seraa/llm/chat_agent.py
seraa/llm/ethical_agent.py
seraa/registry/__init__.py
seraa-0.2.3.dist-info/licenses/LICENSE
utils/__init__.py
seraa-0.2.3.dist-info/METADATA
seraa-0.2.3.dist-info/WHEEL
seraa-0.2.3.dist-info/entry_points.txt
seraa-0.2.3.dist-info/top_level.txt
seraa-0.2.3.dist-info/RECORD
