Metadata-Version: 2.4
Name: seraa
Version: 0.2.3
Summary: Stochastic Emergent Reasoning Alignment Architecture - Ethical AI Framework with PAC evaluation and regulatory benchmarks
Home-page: https://github.com/tpark216/seraa
Author: Theodore Park
Author-email: theodore.jb.park@gmail.com
Project-URL: Bug Tracker, https://github.com/tpark216/seraa/issues
Project-URL: Documentation, https://github.com/tpark216/seraa#readme
Project-URL: Source Code, https://github.com/tpark216/seraa
Project-URL: Benchmarks, https://github.com/tpark216/seraa/tree/main/tests/benchmarks
Keywords: ai-ethics,responsible-ai,ethical-ai,agency-preservation,digital-ethics,moral-reasoning,ai-alignment,llm,ethics-framework,pac,agentic-capacity,regulatory-compliance,gdpr,hipaa,ai-act,benchmark,explainable-ai
Classifier: Development Status :: 4 - Beta
Classifier: Intended Audience :: Science/Research
Classifier: Intended Audience :: Developers
Classifier: Intended Audience :: Education
Classifier: Topic :: Scientific/Engineering :: Artificial Intelligence
Classifier: Topic :: Software Development :: Libraries :: Python Modules
Classifier: Topic :: Scientific/Engineering :: Human Machine Interfaces
Classifier: License :: OSI Approved :: MIT License
Classifier: Programming Language :: Python :: 3
Classifier: Programming Language :: Python :: 3.8
Classifier: Programming Language :: Python :: 3.9
Classifier: Programming Language :: Python :: 3.10
Classifier: Programming Language :: Python :: 3.11
Classifier: Programming Language :: Python :: 3.12
Classifier: Operating System :: OS Independent
Classifier: Natural Language :: English
Requires-Python: >=3.8
License-File: LICENSE
Requires-Dist: requests>=2.31.0
Requires-Dist: numpy>=1.21.0
Provides-Extra: dev
Requires-Dist: pytest>=7.0.0; extra == "dev"
Requires-Dist: pytest-cov>=4.0.0; extra == "dev"
Requires-Dist: pytest-xdist>=3.0.0; extra == "dev"
Requires-Dist: black>=22.0.0; extra == "dev"
Requires-Dist: flake8>=5.0.0; extra == "dev"
Requires-Dist: mypy>=0.990; extra == "dev"
Provides-Extra: llm-full
Requires-Dist: openai>=1.0.0; extra == "llm-full"
Requires-Dist: anthropic>=0.7.0; extra == "llm-full"
Provides-Extra: viz
Requires-Dist: matplotlib>=3.5.0; extra == "viz"
Requires-Dist: seaborn>=0.12.0; extra == "viz"
Provides-Extra: benchmarks
Requires-Dist: matplotlib>=3.5.0; extra == "benchmarks"
Requires-Dist: seaborn>=0.12.0; extra == "benchmarks"
Provides-Extra: all
Requires-Dist: openai>=1.0.0; extra == "all"
Requires-Dist: anthropic>=0.7.0; extra == "all"
Requires-Dist: matplotlib>=3.5.0; extra == "all"
Requires-Dist: seaborn>=0.12.0; extra == "all"
Requires-Dist: pytest>=7.0.0; extra == "all"
Dynamic: author
Dynamic: author-email
Dynamic: classifier
Dynamic: description
Dynamic: description-content-type
Dynamic: home-page
Dynamic: keywords
Dynamic: license-file
Dynamic: project-url
Dynamic: provides-extra
Dynamic: requires-dist
Dynamic: requires-python
Dynamic: summary
